monitor_exporter/__init__.py
monitor_exporter/__main__.py
monitor_exporter/fileconfiguration.py
monitor_exporter/log.py
monitor_exporter/main.py
monitor_exporter/monitorconnection.py
monitor_exporter/perfdata.py
monitor_exporter/proxy.py
tests/__init__.py
tests/test_monitor.py
tests/test_perfdata.py
monitor_exporter-1.3.4.dist-info/COPYING
monitor_exporter-1.3.4.dist-info/LICENSE
monitor_exporter-1.3.4.dist-info/METADATA
monitor_exporter-1.3.4.dist-info/WHEEL
monitor_exporter-1.3.4.dist-info/top_level.txt
monitor_exporter-1.3.4.dist-info/RECORD
