Metadata-Version: 2.1
Name: monitor-exporter
Version: 1.3.4
Summary: A Prometheus exporter for OP5 Monitor
Home-page: https://github.com/opsdis/monitor-exporter
Author: thenodon
Author-email: anders@opsdis.com
License: GPLv3
Requires-Python: >=3.6
License-File: LICENSE
License-File: COPYING
Requires-Dist: aiohttp (>=3.7.4)
Requires-Dist: APScheduler (==3.7.0)
Requires-Dist: prometheus-client (==0.11.0)
Requires-Dist: python-json-logger (==2.0.1)
Requires-Dist: PyYAML (==5.4.1)
Requires-Dist: Quart (==0.17.0)
Requires-Dist: redis (==3.5.3)
Requires-Dist: requests (==2.25.1)
